pytest_pook/__init__.py
pytest_pook/plugin.py
pytest_pook-1.0.0.dist-info/METADATA
pytest_pook-1.0.0.dist-info/WHEEL
pytest_pook-1.0.0.dist-info/entry_points.txt
pytest_pook-1.0.0.dist-info/licenses/LICENSE
pytest_pook-1.0.0.dist-info/RECORD
