Metadata-Version: 2.1
Name: pytest-pook
Version: 1.0.0
Summary: Pytest plugin for pook
Project-URL: Documentation, https://git.sr.ht/~sara/pytest-pook
Project-URL: Source code, https://git.sr.ht/~sara/pytest-pook
Author-email: sarayourfriend <contact@sarayourfriend.pictures>
License-File: LICENSE
Classifier: Development Status :: 4 - Beta
Classifier: Framework :: Pytest
Classifier: Intended Audience :: Developers
Classifier: License :: OSI Approved :: GNU Lesser General Public License v3 (LGPLv3)
Classifier: Programming Language :: Python :: 3
Classifier: Programming Language :: Python :: 3.8
Classifier: Programming Language :: Python :: 3.9
Classifier: Programming Language :: Python :: 3.10
Classifier: Programming Language :: Python :: 3.11
Classifier: Programming Language :: Python :: 3.12
Classifier: Topic :: Software Development :: Testing :: Mocking
Requires-Python: >=3.8
Requires-Dist: pook
Requires-Dist: pytest
